llm_youtube_transcript.py
llm_youtube_transcript-0.2.dist-info/METADATA
llm_youtube_transcript-0.2.dist-info/WHEEL
llm_youtube_transcript-0.2.dist-info/entry_points.txt
llm_youtube_transcript-0.2.dist-info/top_level.txt
llm_youtube_transcript-0.2.dist-info/RECORD
