Metadata-Version: 2.4
Name: llm-youtube-transcript
Version: 0.2
Summary: Plugin for LLM that adds support for fetching transcripts from YouTube videos using Supadata API
Author: Saeed Esmaili
License: Apache-2.0
Requires-Python: >=3.9
Requires-Dist: llm>=0.24
Requires-Dist: httpx
Provides-Extra: test
Requires-Dist: pytest; extra == "test"
Requires-Dist: pytest-httpx; extra == "test"
